{
    "title": "Jenn-Air\u00ae Induction Downdraft Cooktop | Jenn-Air",
    "description": "The Jenn-Air\u00ae Induction Downdraft Cooktop blends our leadership in ventilation with powerful and efficient induction cooking elements. Keeping sight lines open while offering exceptional efficiency and flexibility, this cooktop offers the cooking power of gas and the cleanability of electric while rapidly clearing the air of cooking vapors without the need for an overhead ventilation system. And with smart features, like performance boost for quickly heating cookware to pan detection sensors that automatically turn an element on or off, cooking efficiently and safely has never been easier.",
    "referenceId": "IMvneqeRbM4",
    "date_created": "1482168319",
    "date_modified": "1489012182",
    "tags": "",
    "sourceId": "4",
    "VIDEO_LENGTH": "SHORT",
    "duration": "77",
    "status": "approved",
    "visibility": "1",
    "video_type": "manufacturer",
    "featured_category": null,
    "brand1": "jenn_air",
    "main_category": "appliances",
    "sub_category": "appliances_cooktops",
    "brand_filter": "i_j",
    "sort_order": "sort_order_1",
    "YETI": null,
    "Chantal": null,
    "Rode": null,
    "Rabbit": null,
    "Hunter": null,
    "Casablanca": null,
    "Marshall": null,
    "Thrustmaster": null,
    "First_Alert": null,
    "ANKR": null,
    "Maglite": null,
    "ClassicFlame": null,
    "Zera": null,
    "MantelMount": null,
    "Revolar": null,
    "JOBY": null,
    "Coyote": null,
    "Amplifi": null,
    "Solidsteel": null,
    "The_Galley": null,
    "Shavel": null,
    "Zeiss": null,
    "Chipolo": null,
    "mJoose": null,
    "B_W_International": null,
    "Luminox": null,
    "Lifesmart": null,
    "Muzik": null,
    "RadarMount": null,
    "VV_VI": "56",
    "CVV_VI": null,
    "engagement_score": null,
    "conversion_score": null,
    "id": "83102532",
    "loginId": "1758854",
    "entityType": "1",
    "titleTextEncoded": "Jenn-Air-Induction-Downdraft-Cooktop-Jenn-Air",
    "category": "",
    "settings": "",
    "asset": {
        "type": "youtube",
        "thumbnailUrl": "https:\/\/i.ytimg.com\/vi\/IMvneqeRbM4\/hqdefault.jpg",
        "uploadDate": 1482168319,
        "videoId": "IMvneqeRbM4",
        "title": "Jenn-Air\u00ae Induction Downdraft Cooktop | Jenn-Air",
        "description": "The Jenn-Air\u00ae Induction Downdraft Cooktop blends our leadership in ventilation with powerful and efficient induction cooking elements. Keeping sight lines open while offering exceptional efficiency and flexibility, this cooktop offers the cooking power of gas and the cleanability of electric while rapidly clearing the air of cooking vapors without the need for an overhead ventilation system. And with smart features, like performance boost for quickly heating cookware to pan detection sensors that automatically turn an element on or off, cooking efficiently and safely has never been easier. \n\nTo find out more about the Induction Downdraft Cooktop visit:\nhttps:\/\/jennair.com\/appliances\/details\/JID4436ES \n\nFollow Jenn-Air on Facebook at:\nhttps:\/\/www.facebook.com\/JennAir\n\nFollow Jenn-Air on Instagram at: \nhttps:\/\/instagram.com\/jennairusa\/\n\nFollow Jenn-Air on Twitter at:\nhttps:\/\/twitter.com\/jennairUSA\n\nFollow Jenn-Air on Houzz at:\nhttp:\/\/www.houzz.com\/user\/jennairusa",
        "author": "Jenn-Air",
        "mediaDuration": 77,
        "prettyDuration": "00:01:17",
        "views": "23",
        "uploadAsset": false,
        "quality": ""
    },
    "transcripts": "",
    "metrics_statistics": "{\"VV_VI\":{\"lastUpdatedDate\":\"2017-05-22\",\"engagement_score\":{\"lastUpdatedDate\":\"2017-05-26\"}}}",
    "tvp_concept": [
        "HVAC",
        "HVAC"
    ],
    "tvp_entity_company": null,
    "tvp_entity_facility": null,
    "tvp_entity_geographicfeature": null,
    "tvp_entity_healthcondition": null,
    "tvp_entity_location": null,
    "tvp_entity_movie": null,
    "tvp_entity_musicgroup": null,
    "tvp_entity_organization": null,
    "tvp_entity_person": null,
    "tvp_entity_sport": null,
    "tvp_entity_sportingevent": null,
    "tvp_entity_televisionshow": null,
    "tvp_entity_twitterhandle": null,
    "tvp_entity_vehicle": null,
    "tvp_category_1": [
        "\/home and garden"
    ],
    "tvp_category_2": [
        "\/home and garden\/appliances"
    ],
    "tvp_category_3": null,
    "tvp_category_4": null,
    "tvp_category_5": null,
    "tvp_profiles": [
        "30",
        "18",
        "14"
    ],
    "tvp_profiles_manual": null,
    "tvp_profiles_maxscore": 9716.427
}